pedophysics/__init__.py
pedophysics/instruments.py
pedophysics/main.py
pedophysics/simulate.py
pedophysics/pedophysical_models/__init__.py
pedophysics/pedophysical_models/bulk_ec.py
pedophysics/pedophysical_models/bulk_perm.py
pedophysics/pedophysical_models/water.py
pedophysics/pedophysical_models/water_ec.py
pedophysics/pedophysical_models/water_perm.py
pedophysics/pedotransfer_functions/__init__.py
pedophysics/pedotransfer_functions/particle_density.py
pedophysics/predict/__init__.py
pedophysics/predict/air_perm.py
pedophysics/predict/bulk_ec.py
pedophysics/predict/bulk_ec_dc.py
pedophysics/predict/bulk_ec_dc_tc.py
pedophysics/predict/bulk_ec_tc.py
pedophysics/predict/bulk_perm.py
pedophysics/predict/bulk_perm_inf.py
pedophysics/predict/frequency_ec.py
pedophysics/predict/frequency_perm.py
pedophysics/predict/particle_density.py
pedophysics/predict/porosity.py
pedophysics/predict/salinity.py
pedophysics/predict/solid_ec.py
pedophysics/predict/solid_perm.py
pedophysics/predict/temperature.py
pedophysics/predict/texture.py
pedophysics/predict/water.py
pedophysics/predict/water_ec.py
pedophysics/predict/water_from_ec.py
pedophysics/predict/water_from_perm.py
pedophysics/predict/water_perm.py
pedophysics/utils/similar_arrays.py
pedophysics/utils/stats.py
pedophysics-0.1.5.dist-info/licenses/LICENSE.txt
pedophysics-0.1.5.dist-info/METADATA
pedophysics-0.1.5.dist-info/WHEEL
pedophysics-0.1.5.dist-info/top_level.txt
pedophysics-0.1.5.dist-info/RECORD
