Metadata-Version: 2.4
Name: Pedophysics
Version: 0.1.5
Summary: A Python package for soil electromagnetic geophysics
Author-email: Gaston Matias Mendoza Veirana <mendoveirana@gmail.com>
Project-URL: Homepage, https://github.com/SENSE-UGent/Pedophysics
Project-URL: Repository, https://github.com/SENSE-UGent/Pedophysics
Project-URL: Documentation, https://sense-ugent.github.io/Pedophysics/build/html/index.html
Project-URL: Issues, https://github.com/SENSE-UGent/Pedophysics/issues
Keywords: soil,geophysics,petrophysics,pedophysics
Classifier: Programming Language :: Python :: 3
Classifier: License :: OSI Approved :: MIT License
Classifier: Operating System :: OS Independent
Requires-Python: >=3.7
License-File: LICENSE.txt
Requires-Dist: numpy
Requires-Dist: matplotlib
Requires-Dist: pandas
Requires-Dist: scipy
Dynamic: license-file
